MANIFEST.in
README.rst
setup.py
src/requests_testadapter.py
src/requests_testadapter.egg-info/PKG-INFO
src/requests_testadapter.egg-info/SOURCES.txt
src/requests_testadapter.egg-info/dependency_links.txt
src/requests_testadapter.egg-info/not-zip-safe
src/requests_testadapter.egg-info/requires.txt
src/requests_testadapter.egg-info/top_level.txt
test/test_testadapter.py