Metadata-Version: 1.1
Name: requests-testadapter
Version: 0.3.0
Summary: Provides an adapter for mocking HTTP requests for unit test purposes.
Home-page: https://github.com/ambv/requests-testadapter
Author: Łukasz Langa
Author-email: lukasz@langa.pl
License: MIT
Keywords: requests unit testing tests mock http
Platform: any
Classifier: Development Status :: 3 - Alpha
Classifier: Intended Audience :: Developers
Classifier: License :: OSI Approved :: MIT License
Classifier: Natural Language :: English
Classifier: Operating System :: OS Independent
Classifier: Programming Language :: Python
Classifier: Programming Language :: Python :: 2
Classifier: Programming Language :: Python :: 2.6
Classifier: Programming Language :: Python :: 2.7
Classifier: Programming Language :: Python :: 3
Classifier: Programming Language :: Python :: 3.2
Classifier: Programming Language :: Python :: 3.3
Classifier: Topic :: Software Development :: Libraries :: Python Modules
